[
    {
        "ID": 1,
        "Scenario_ID": "CP1-1",
        "SA_atoms": "Speed",
        "SA_Level": "Perception",
        "Awareness_to": "Myself",
        "Participant": [
            "A",
            "B"
        ],
        "QuestionText": {
            "English": "How fast were you driving before the intersection?",
            "Hebrew": "מה הייתה המהירות שלך בזמן שהתקרבת לצומת?"
        },
        "Answers": [
            {
                "index": 1,
                "AnswerText": {
                    "English": "High speed",
                    "Hebrew": "מהירה"
                }
            },
            {
                "index": 2,
                "AnswerText": {
                    "English": "Normal speed",
                    "Hebrew": "נורמאלית"
                }
            },
            {
                "index": 3,
                "AnswerText": {
                    "English": "Slow speed",
                    "Hebrew": "איטית"
                }
            },
            {
                "index": 4,
                "AnswerText": {
                    "English": "I'm not sure",
                    "Hebrew": "אני לא בטוח"
                }
            }
        ]
    },
    {
        "ID": 11,
        "Scenario_ID": "CP1-11",
        "SA_atoms": "Speed",
        "SA_Level": "Comprehension",
        "Awareness_to": "Myself",
        "Participant": [
            "A",
            "B"
        ],
        "QuestionText": {
            "English": "As you approached the intersection, how was your speed changing?",
            "Hebrew": "מה שינית במהירות שלך בזמן שהתקרבת לצומת?"
        },
        "Answers": [
            {
                "index": 1,
                "AnswerText": {
                    "English": "I was slowing down",
                    "Hebrew": "האטתי"
                }
            },
            {
                "index": 2,
                "AnswerText": {
                    "English": "I was accelerating",
                    "Hebrew": "האצתי"
                }
            },
            {
                "index": 3,
                "AnswerText": {
                    "English": "I didn't changed my speed",
                    "Hebrew": "לא שיניתי את המהירות שלי"
                }
            },
            {
                "index": 4,
                "AnswerText": {
                    "English": "I'm not sure",
                    "Hebrew": "אני לא בטוח"
                }
            }
        ]
    },
    {
        "ID": 18,
        "Scenario_ID": "CP1-18",
        "SA_atoms": "Signaling",
        "SA_Level": "Perception",
        "Awareness_to": "Myself",
        "Participant": [
            "A",
            "B"
        ],
        "QuestionText": {
            "English": "As you approached the intersection, did you signal?",
            "Hebrew": "בזמן שהתקרבת לצומת, האם אותתתה?"
        },
        "Answers": [
            {
                "index": 1,
                "AnswerText": {
                    "English": "Yes",
                    "Hebrew": "כן"
                }
            },
            {
                "index": 2,
                "AnswerText": {
                    "English": "No",
                    "Hebrew": "לא"
                }
            },
            {
                "index": 3,
                "AnswerText": {
                    "English": "I'm not sure",
                    "Hebrew": "אני לא בטוח"
                }
            }
        ]
    },
    {
        "ID": 19,
        "Scenario_ID": "CP1-19",
        "SA_atoms": "Heading",
        "SA_Level": "Perception",
        "Awareness_to": "Myself",
        "Participant": [
            "A",
            "B"
        ],
        "QuestionText": {
            "English": "As you approached the intersection, what direction were you heading?",
            "Hebrew": "בזמן שהתקרבת לצומת, לאיזה כיוון הרכב שלך פנה?"
        },
        "Answers": [
            {
                "index": 1,
                "AnswerText": {
                    "English": "To the right",
                    "Hebrew": "ימינה"
                }
            },
            {
                "index": 2,
                "AnswerText": {
                    "English": "To the left",
                    "Hebrew": "שמאלה"
                }
            },
            {
                "index": 3,
                "AnswerText": {
                    "English": "Straight",
                    "Hebrew": "ישר"
                }
            },
            {
                "index": 4,
                "AnswerText": {
                    "English": "I'm not sure",
                    "Hebrew": "אני לא בטוח"
                }
            }
        ]
    },
    {
        "ID": 16,
        "Scenario_ID": "CP1-16",
        "SA_atoms": "Heading",
        "SA_Level": "Projection",
        "Awareness_to": "Other driver",
        "Participant": [
            "A",
            "B"
        ],
        "QuestionText": {
            "English": "Did you feel there was a risk of a collision at that intersection?",
            "Hebrew":"האם חשת שעשויה להיות התנגשות בצומת?"
                  },
        "Answers": [
            {
                "index": 1,
                "AnswerText": {
                    "English": "Yes",
                    "Hebrew": "כן"
                }
            },
            {
                "index": 2,
                "AnswerText": {
                    "English": "No",
                    "Hebrew": "לא"
                }
            },
            {
                "index": 3,
                "AnswerText": {
                    "English": "I'm not sure",
                    "Hebrew": "אני לא בטוח"
                }
            }
        ]
    },
    {
        "ID": 25,
        "Scenario_ID": "CP1-25",
        "SA_atoms": "Environment",
        "SA_Level": "Perception",
        "Awareness_to": "Other driver",
        "Participant": [
            "A",
            "B"
        ],
        "QuestionText": {
            "English": "As you approached the intersection, did you notice another vehicle?",
            "Hebrew": "בזמן שהתקרבת לצומת, האם שמת לב לרכב נוסף?"
        },
        "Answers": [
            {
                "index": 1,
                "AnswerText": {
                    "English": "Yes",
                    "Hebrew": "כן"
                }
            },
            {
                "index": 2,
                "AnswerText": {
                    "English": "No",
                    "Hebrew": "לא"
                }
            },
            {
                "index": 3,
                "AnswerText": {
                    "English": "I'm not sure",
                    "Hebrew": "אני לא בטוח"
                }
            }
        ]
    },
    {
        "ID": 9,
        "Scenario_ID": "CP1-9",
        "SA_atoms": "Speed",
        "SA_Level": "Perception",
        "Awareness_to": "Other driver",
        "Participant": [
            "A",
            "B"
        ],
        "QuestionText": {
            "English": "How fast was the other driver driving before the intersection?",
            "Hebrew": "מה הייתה המהירות של הנהג השני לפני הצומת?"
        },
        "Answers": [
            {
                "index": 1,
                "AnswerText": {
                    "English": "High speed",
                    "Hebrew": "מהירה"
                }
            },
            {
                "index": 2,
                "AnswerText": {
                    "English": "Normal speed",
                    "Hebrew": "נורמאלית"
                }
            },
            {
                "index": 3,
                "AnswerText": {
                    "English": "Slow speed",
                    "Hebrew": "איטית"
                }
            },
            {
                "index": 4,
                "AnswerText": {
                    "English": "I'm not sure",
                    "Hebrew": "אני לא בטוח"
                }
            }
        ]
    },
    {
        "ID": 10,
        "Scenario_ID": "CP1-10",
        "SA_atoms": "Speed",
        "SA_Level": "Comprehension",
        "Awareness_to": "Other driver",
        "Participant": [
            "A",
            "B"
        ],
        "QuestionText": {
            "English": "As you approached the intersection, how the other driver's speed changing?",
            "Hebrew": "כיצד המהירות של הנהג השני השתנתה בזמן שהתקרבת לצומת?"
        },
        "Answers": [
            {
                "index": 1,
                "AnswerText": {
                    "English": "They were slowing down",
                    "Hebrew": "הוא האט"
                }
            },
            {
                "index": 2,
                "AnswerText": {
                    "English": "They were accelerating",
                    "Hebrew": "הוא האיץ"
                }
            },
            {
                "index": 3,
                "AnswerText": {
                    "English": "They didn't change their speed",
                    "Hebrew": "הוא לא שינה את המהירות שלו"
                }
            },
            {
                "index": 4,
                "AnswerText": {
                    "English": "I'm not sure",
                    "Hebrew": "אני לא בטוח"
                }
            }
        ]
    },
    {
        "ID": 15,
        "Scenario_ID": "CP1-15",
        "SA_atoms": "Speed",
        "SA_Level": "Projection",
        "Awareness_to": "Other driver",
        "Participant": [
            "A",
            "B"
        ],
        "QuestionText": {
            "English": "What did you expect the other vehicle to do when you noticed it?",
            "Hebrew": "מה ציפית שהרכב השני יעשה כאשר שמת לב אליו?"
        },
        "Answers": [
            {
                "index": 1,
                "AnswerText": {
                    "English": "Come to a complete stop",
                    "Hebrew": "יעצור לחלוטין"
                }
            },
            {
                "index": 2,
                "AnswerText": {
                    "English": "Continue at the same pace and enter the intersection",
                    "Hebrew": "ימשיך באותה מהירות ויכנס לצומת"
                }
            },
            {
                "index": 3,
                "AnswerText": {
                    "English": "Slow down and move slowly into the intersection",
                    "Hebrew": "יאט ויכנס באיטיות לצומת"
                }
            },
            {
                "index": 4,
                "AnswerText": {
                    "English": "I'm not sure",
                    "Hebrew": "אני לא בטוח"
                }
            }
        ]
    },
    {
        "ID": 4,
        "Scenario_ID": "CP1-4",
        "SA_atoms": "Location",
        "SA_Level": "Perception",
        "Awareness_to": "Other driver",
        "Participant": [
            "A",
            "B"
        ],
        "QuestionText": {
            "English": "What direction was the other vehicle coming from?",
            "Hebrew": "מאיזה כיוון הרכב השני הגיע?"
        },
        "Answers": [
            {
                "index": 1,
                "AnswerText": {
                    "English": "To my left, on the opposite lane",
                    "Hebrew": "מהנתיב מולי מצד שמאל"
                }
            },
            {
                "index": 2,
                "AnswerText": {
                    "English": "On the opposite side of the road to my right",
                    "Hebrew": "מהנתיב מולי מצד ימין"
                }
            },
            {
                "index": 3,
                "AnswerText": {
                    "English": "To my right, on the orthogonal lane",
                    "Hebrew": "מהנתיב מצד ימין"
                }
            },
            {
                "index": 4,
                "AnswerText": {
                    "English": "To my left, on the orthogonal lane",
                    "Hebrew": "מהנתיב מצד שמאל"
                }
            },
            {
                "index": 5,
                "AnswerText": {
                    "English": "I'm not sure",
                    "Hebrew": "אני לא בטוח"
                }
            }
        ]
    },
    {
        "ID": 7,
        "Scenario_ID": "CP1-7",
        "SA_atoms": "Location",
        "SA_Level": "Comprehension",
        "Awareness_to": "Both",
        "Participant": [
            "A",
            "B"
        ],
        "QuestionText": {
            "English": "Who had the right of way?",
            "Hebrew": "למי הייתה זכות קדימה?"
        },
        "Answers": [
            {
                "index": 1,
                "AnswerText": {
                    "English": "Me",
                    "Hebrew": "לי"
                }
            },
            {
                "index": 2,
                "AnswerText": {
                    "English": "The other vehicle",
                    "Hebrew": "לנהג השני"
                }
            },
            {
                "index": 3,
                "AnswerText": {
                    "English": "Both of us",
                    "Hebrew": "לשנינו"
                }
            },
            {
                "index": 4,
                "AnswerText": {
                    "English": "Neither of us",
                    "Hebrew":  "לאף אחד מאיתנו"
                }
            },
            {
                "index": 5,
                "AnswerText": {
                    "English": "I'm not sure",
                    "Hebrew": "אני לא בטוח"
                }
            }
        ]
    },
    {
        "ID": 8,
        "Scenario_ID": "CP1-8",
        "SA_atoms": "Location",
        "SA_Level": "Projection",
        "Awareness_to": "Both",
        "Participant": [
            "A",
            "B"
        ],
        "QuestionText": {
            "English": "Given the right-of-way, what could have happened next?",
            "Hebrew": "בהינתן זכות הקדימה, מה היה עשוי לקרות?"
        },
        "Answers": [
            {
                "index": 1,
                "AnswerText": {
                    "English": "The other driver would have crossed the intersection first",
                    "Hebrew": "הנהג השני עשוי היה לחצות את הצומת"
                }
            },
            {
                "index": 2,
                "AnswerText": {
                    "English": "The other driver would not have crossed the intersection first",
                    "Hebrew": "הנהג השני לא היה חוצה את הצומת"
                }
            },
            {
                "index": 3,
                "AnswerText": {
                    "English": "I am not sure",
                    "Hebrew": "אני לא בטוח"
                }
            }
        ]
    },
    {
        "ID": 2,
        "Scenario_ID": "CP1-2",
        "SA_atoms": "Signaling",
        "SA_Level": "Perception",
        "Awareness_to": "Other driver",
        "Participant": [
            "A",
            "B"
        ],
        "QuestionText": {
            "English": "Did the other vehicle signal as it approached the intersection?",
            "Hebrew": "האם הרכב השני אותת בזמן שהוא התקרב לצומת?"
        },
        "Answers": [
            {
                "index": 1,
                "AnswerText": {
                    "English": "Yes",
                    "Hebrew": "כן"
                }
            },
            {
                "index": 2,
                "AnswerText": {
                    "English": "No",
                    "Hebrew": "לא"
                }
            },
            {
                "index": 3,
                "AnswerText": {
                    "English": "I'm not sure",
                    "Hebrew": "אני לא בטוח"
                }
            }
        ]
    },
    {
        "ID": 14,
        "Scenario_ID": "CP1-14",
        "SA_atoms": "Heading",
        "SA_Level": "Perception",
        "Awareness_to": "Other driver",
        "Participant": [
            "A",
            "B"
        ],
        "QuestionText": {
            "English": "Going into the intersection, which direction was the other vehicle heading?",
            "Hebrew": "בזמן שהתקרבת לצומת, לאיזה כיוון פנה הנהג השני?"
        },
        "Answers": [
            {
                "index": 1,
                "AnswerText": {
                    "English": "To the right",
                    "Hebrew": "לימין"
                }
            },
            {
                "index": 2,
                "AnswerText": {
                    "English": "To the left",
                    "Hebrew": "לשמאל"
                }
            },
            {
                "index": 3,
                "AnswerText": {
                    "English": "Straight",
                    "Hebrew": "ישר"
                }
            },
            {
                "index": 4,
                "AnswerText": {
                    "English": "I'm not sure",
                    "Hebrew": "אני לא בטוח"
                }
            }
        ]
    },
    {
        "ID": 17,
        "Scenario_ID": "CP1-17",
        "SA_atoms": "Signaling",
        "SA_Level": "Comprehension",
        "Awareness_to": "Other driver",
        "Participant": [
            "A",
            "B"
        ],
        "QuestionText": {
            "English": "Before crossing the intersection, which direction did you think the other driver was going in?",
            "Hebrew": "לפני שחצית את הצומת, לאיזה כיוון חשבת שהנהג השני עשוי לפנות?"
        },
        "Answers": [
            {
                "index": 1,
                "AnswerText": {
                    "English": "Heading straight",
                    "Hebrew": "ישר"
                }
            },
            {
                "index": 2,
                "AnswerText": {
                    "English": "Turning right",
                    "Hebrew": "ימינה"
                }
            },
            {
                "index": 3,
                "AnswerText": {
                    "English": "Turning left",
                    "Hebrew": "שמאלה"
                }
            },
            {
                "index": 4,
                "AnswerText": {
                    "English": "I'm not sure",
                    "Hebrew": "אני לא בטוח"
                }
            }
        ]
    },
    {
        "ID": 13,
        "Scenario_ID": "CP1-13",
        "SA_atoms": "Heading",
        "SA_Level": "Projection",
        "Awareness_to": "Other driver",
        "Participant": [
            "A",
            "B"
        ],
        "QuestionText": {
            "English": "While the other driver was approaching the intersection, I could tell that:",
            "Hebrew":"בזמן שהנהג השני התקרב לצומת, מה היה עשוי לקרות להערכתך?"
        },
        "Answers": [
            {
                "index": 1,
                "AnswerText": {
                    "English": "The other driver was going to turn right",
                    "Hebrew": "הנהג השני היה פונה ימינה"
                }
            },
            {
                "index": 2,
                "AnswerText": {
                    "English": "The other driver was going to turn left",
                    "Hebrew": "הנהג השני היה פונה שמאלה"
                }
            },
            {
                "index": 3,
                "AnswerText": {
                    "English": "The other driver was going to go straight",
                    "Hebrew": "הנהג השני היה ממשיך ישר"
                }
            },
            {
                "index": 4,
                "AnswerText": {
                    "English": "I'm not sure",
                    "Hebrew": "אני לא בטוח"
                }
            }
        ]
    },
    {
        "ID": 20,
        "Scenario_ID": "CP1-20",
        "SA_atoms": "Heading",
        "SA_Level": "Perception",
        "Awareness_to": "Other driver",
        "Participant": [
            "A",
            "B"
        ],
        "QuestionText": {
            "English": "Who was the first one to enter the intersection?",
            "Hebrew": "מי הראשון שנכנס לצומת?"
        },
        "Answers": [
            {
                "index": 1,
                "AnswerText": {
                    "English": "I was",
                    "Hebrew": "אני"
                }
            },
            {
                "index": 2,
                "AnswerText": {
                    "English": "The other vehicle",
                    "Hebrew": "הרכב השני"
                }
            },
            {
                "index": 3,
                "AnswerText": {
                    "English": "Both of us",
                    "Hebrew": "שנינו"
                }
            },
            {
                "index": 4,
                "AnswerText": {
                    "English": "I'm not sure",
                    "Hebrew": "אני לא בטוח"
                }
            }
        ]
    },
    {
        "ID": 3,
        "Scenario_ID": "CP1-3",
        "SA_atoms": "Location",
        "SA_Level": "Perception",
        "Awareness_to": "Other driver",
        "Participant": [
            "A",
            "B"
        ],
        "QuestionText": {
            "English": "As you entered the intersection, what was the location of the other vehicle?",
            "Hebrew": "בזמן שנכנסת לצומת, מה היה המיקום של הרכב השני?"
        },
        "Answers": [
            {
                "index": 1,
                "AnswerText": {
                    "English": "I didn't notice / Can't remember",
                    "Hebrew": "לא שמתי לב / לא זוכר"
                }
            },
            {
                "index": 2,
                "AnswerText": {
                    "English": "In the middle of the intersection",
                    "Hebrew": "בתוך הצומת"
                }
            },
            {
                "index": 3,
                "AnswerText": {
                    "English": "Before the intersection",
                    "Hebrew": "לפני הצומת"
                }
            },
            {
                "index": 4,
                "AnswerText": {
                    "English": "After the intersection",
                    "Hebrew": "אחרי הצומת"
                }
            },
            {
                "index": 5,
                "AnswerText": {
                    "English": "I didn't have a chance to get into the intersection",
                    "Hebrew": "לא הספקתי להכנס לצומת"
                }
            },
            {
                "index": 6,
                "AnswerText": {
                    "English": "I'm not sure",
                    "Hebrew": "אני לא בטוח"
                }
            }
        ]
    }
]
